<?xml version="1.0"?>
<instance entity-name="altera_fir_compiler_ii" version="14.1" >
<generic name="filterType" value="single" />
<generic name="interpFactor" value="1" />
<generic name="decimFactor" value="1" />
<generic name="symmetryMode" value="nsym" />
<generic name="L_bandsFilter" value="1" />
<generic name="inputChannelNum" value="1" />
<generic name="clockRate" value="8" />
<generic name="clockSlack" value="1" />
<generic name="inputRate" value="8" />
<generic name="coeffReload" value="false" />
<generic name="baseAddress" value="0" />
<generic name="readWriteMode" value="read_write" />
<generic name="backPressure" value="false" />
<generic name="deviceFamily" value="Cyclone V" />
<generic name="speedGrade" value="medium" />
<generic name="delayRAMBlockThreshold" value="20" />
<generic name="dualMemDistRAMThreshold" value="1280" />
<generic name="mRAMThreshold" value="1000000" />
<generic name="hardMultiplierThreshold" value="-1" />
<generic name="inputType" value="int" />
<generic name="inputBitWidth" value="8" />
<generic name="inputFracBitWidth" value="0" />
<generic name="coeffSetRealValue" value="-2.501181074493E-19,-1.31040709340593E-4,-2.67846426461749E-4,-4.09705302915656E-4,-5.53245155806145E-4,-6.91403080469304E-4,-8.12895000127837E-4,-9.02346379107985E-4,-9.41175555793902E-4,-9.09234662524505E-4,-7.87118273393985E-4,-5.58956481603788E-4,-2.15427205859483E-4,2.43338259369895E-4,8.05314073408612E-4,0.00144495757038627,0.00212272001713453,0.00278592793854673,0.0033711642840312,0.00380814677190114,0.00402495587762903,0.00395431979773709,0.00354053184409333,0.00274647027130379,0.00156012310464874,-1.68829722528278E-18,-0.00188115523480563,-0.00399485315919589,-0.00621791587995295,-0.00839629516829185,-0.0103516393296478,-0.0118903783386811,-0.0128148818346288,-0.0129360508401096,-0.0120865484076927,-0.0101337713336222,-0.00699162545795516,-0.00263019704244412,0.00291748694381661,0.00955225093377586,0.0171095354032093,0.0253642926602391,0.0340398891138202,0.0428206051158104,0.0513670597263753,0.0593336648601417,0.0663870488753555,0.0722242972521807,0.0765898457582718,0.0792899315985133,0.0802036564174653,0.0792899315985133,0.0765898457582718,0.0722242972521807,0.0663870488753555,0.0593336648601417,0.0513670597263753,0.0428206051158104,0.0340398891138202,0.0253642926602391,0.0171095354032093,0.00955225093377586,0.00291748694381661,-0.00263019704244412,-0.00699162545795516,-0.0101337713336222,-0.0120865484076927,-0.0129360508401096,-0.0128148818346288,-0.0118903783386811,-0.0103516393296478,-0.00839629516829185,-0.00621791587995295,-0.00399485315919589,-0.00188115523480563,-1.68829722528278E-18,0.00156012310464874,0.00274647027130379,0.00354053184409333,0.00395431979773709,0.00402495587762903,0.00380814677190114,0.0033711642840312,0.00278592793854673,0.00212272001713453,0.00144495757038627,8.05314073408612E-4,2.43338259369895E-4,-2.15427205859483E-4,-5.58956481603788E-4,-7.87118273393985E-4,-9.09234662524505E-4,-9.41175555793902E-4,-9.02346379107985E-4,-8.12895000127837E-4,-6.91403080469304E-4,-5.53245155806145E-4,-4.09705302915656E-4,-2.67846426
<generic name="coeffScaling" value="auto" />
<generic name="coeffType" value="int" />
<generic name="coeffBitWidth" value="12" />
<generic name="coeffFracBitWidth" value="0" />
<generic name="outType" value="int" />
<generic name="outMSBRound" value="trunc" />
<generic name="outMsbBitRem" value="0" />
<generic name="outLSBRound" value="trunc" />
<generic name="outLsbBitRem" value="0" />
<generic name="bankCount" value="1" />
<generic name="bankDisplay" value="0" />
</instance>
